LICENSE
README.md
setup.py
epicstore_api/__init__.py
epicstore_api/api.py
epicstore_api/exc.py
epicstore_api/queries.py
epicstore_api.egg-info/PKG-INFO
epicstore_api.egg-info/SOURCES.txt
epicstore_api.egg-info/dependency_links.txt
epicstore_api.egg-info/requires.txt
epicstore_api.egg-info/top_level.txt
epicstore_api/models/__init__.py
epicstore_api/models/categories.py
epicstore_api/models/collection_types.py
epicstore_api/models/product_types.py