Metadata-Version: 2.1
Name: epicstore-api
Version: 0.1.7
Summary: An API wrapper for Epic Games Store written in Python
Home-page: https://github.com/SD4RK/epicstore_api
Download-URL: https://github.com/SD4RK/epicstore_api/archive/v_0.1.7.tar.gz
Author: SD4RK
License: MIT
Classifier: License :: OSI Approved :: MIT License
Classifier: Intended Audience :: Developers
Classifier: Natural Language :: English
Classifier: Operating System :: OS Independent
Classifier: Programming Language :: Python :: 3.7
Classifier: Programming Language :: Python :: 3.8
Classifier: Programming Language :: Python :: 3.9
Classifier: Programming Language :: Python :: 3.10
Classifier: Topic :: Internet
Classifier: Topic :: Software Development :: Libraries
Classifier: Topic :: Software Development :: Libraries :: Python Modules
Classifier: Topic :: Utilities
Requires-Python: >=3.7
License-File: LICENSE
